{
  "books": [
    {
      "id": 1,
      "signatura": "E-Gen",
      "titol": "Cartas / Artemisia Gentileschi. Precedidas de las Actas del proceso por estupro / prólogo de Estrella de Diego",
      "autoria": "Gentileschi, Artemisia",
      "descriptors": "Epistolaris",
      "isbn": "9788437635286",
      "observacions": null,
      "image": "https://images-na.ssl-images-amazon.com/images/I/81xXMXLaCwL.jpg"
    },
    {
      "id": 2,
      "signatura": "10.04.04 Abd",
      "titol": "De qué hablamos cuando hablamos de violación",
      "autoria": "Abdulalí, Sohaila",
      "descriptors": "Violacions/ Delictes sexuals/ Víctimes / Violència",
      "isbn": "9788437640792",
      "observacions": null,
      "image": "https://images-na.ssl-images-amazon.com/images/I/41ChOET2JUL._SX342_SY445_QL70_ML2_.jpg"
    },
    {
      "id": 3,
      "signatura": "B-Abe",
      "titol": "Miracle és viure",
      "autoria": "Abelló, Montserrat",
      "descriptors": "Biografies/ Escriptores/ Poetes/ Poesia",
      "isbn": "9788415642855",
      "observacions": null,
      "image": "https://images-na.ssl-images-amazon.com/images/I/710to9Bwt5L.jpg"
    },
    {
      "id": 4,
      "signatura": "P-Abe",
      "titol": "Cares a la finestra: 20 dones poetes de parla anglesa del segle XX",
      "autoria": "Abelló, Montserrat",
      "descriptors": "Poesia/ Poetes",
      "isbn": "9788481098914",
      "observacions": "Comanda oct. 21, PRÒLEG",
      "image": "https://cloud10.todocoleccion.online/libros-segunda-mano-poesia/tc/2013/10/23/39626599.jpg"
    },
    {
      "id": 5,
      "signatura": "12.08 Fem",
      "titol": "Feminismo y modernidad en Oriente Próximo",
      "autoria": "Abu-Lughod, Lila (Ed.)",
      "descriptors": "Feminisme/ Islam/ Dones àrabs/ Multiculturalisme",
      "isbn": "9788437619958",
      "observacions": null,
      "image": "https://www.catedra.com/imagenes/libros/grande/9788437619958-feminismo-y-modernidad-en-oriente-proximo.jpg"
    },
    {
      "id": 6,
      "signatura": "04.04 Ack",
      "titol": "Mujeres libres: El anarquismo y la lucha por la emancipación de las mujeres",
      "autoria": "Ackelsberg, Martha",
      "descriptors": "Anarquistes/ Història de les dones/ Conflictes bèl·lics",
      "isbn": "9788492559794",
      "observacions": "Expositor",
      "image": "https://www.alibri.es/image/cache/covers/e/f/697583-360x480.jpg"
    }
  ]
}